otio_drp_adapter/__init__.py
otio_drp_adapter/plugin_manifest.json
otio_drp_adapter/adapters/__init__.py
otio_drp_adapter/adapters/drp.py
otio_drp_adapter-0.2.1.dist-info/LICENSE-APACHE-20
otio_drp_adapter-0.2.1.dist-info/LICENSE.md
otio_drp_adapter-0.2.1.dist-info/METADATA
otio_drp_adapter-0.2.1.dist-info/WHEEL
otio_drp_adapter-0.2.1.dist-info/entry_points.txt
otio_drp_adapter-0.2.1.dist-info/top_level.txt
otio_drp_adapter-0.2.1.dist-info/RECORD
