Metadata-Version: 2.1
Name: otio-drp-adapter
Version: 0.2.1
Summary: OpenTimelineIO adapter plugin for .drp files
Home-page: https://github.com/gilou/otio-drp-adapter
Author: Gilou
Author-email: contact+dev@gilouweb.com
License: UNKNOWN
Platform: UNKNOWN
Classifier: Development Status :: 4 - Beta
Classifier: Intended Audience :: Developers
Classifier: Topic :: Multimedia :: Video
Classifier: Topic :: Multimedia :: Video :: Display
Classifier: Topic :: Multimedia :: Video :: Non-Linear Editor
Classifier: Topic :: Software Development :: Libraries :: Python Modules
Classifier: Programming Language :: Python :: 2
Classifier: Programming Language :: Python :: 2.7
Classifier: Programming Language :: Python :: 3
Classifier: Programming Language :: Python :: 3.7
Classifier: Programming Language :: Python :: 3.8
Classifier: Operating System :: OS Independent
Classifier: License :: OSI Approved :: Apache Software License
Classifier: Natural Language :: English
License-File: LICENSE-APACHE-20
License-File: LICENSE.md
Requires-Dist: OpenTimelineIO (>=0.12.0)
Provides-Extra: dev
Requires-Dist: flake8 ; extra == 'dev'
Requires-Dist: pytest ; extra == 'dev'
Requires-Dist: twine ; extra == 'dev'
